datasette_granian/__init__.py
datasette_granian-0.1.dist-info/LICENSE
datasette_granian-0.1.dist-info/METADATA
datasette_granian-0.1.dist-info/WHEEL
datasette_granian-0.1.dist-info/entry_points.txt
datasette_granian-0.1.dist-info/top_level.txt
datasette_granian-0.1.dist-info/RECORD
