Metadata-Version: 2.1
Name: datasette-granian
Version: 0.1
Summary: Run Datasette using the Granian HTTP server
Home-page: https://github.com/simonw/datasette-granian
Author: Simon Willison
License: Apache License, Version 2.0
Project-URL: Issues, https://github.com/simonw/datasette-granian/issues
Project-URL: CI, https://github.com/simonw/datasette-granian/actions
Project-URL: Changelog, https://github.com/simonw/datasette-granian/releases
Classifier: Framework :: Datasette
Classifier: License :: OSI Approved :: Apache Software License
Requires-Python: >=3.8
License-File: LICENSE
Requires-Dist: datasette
Requires-Dist: granian
Provides-Extra: test
Requires-Dist: pytest ; extra == 'test'
Requires-Dist: pytest-asyncio ; extra == 'test'
Requires-Dist: datasette-test ; extra == 'test'
